bagpy/README.md
bagpy/__init__.py
bagpy/bagreader.py
bagpy/version
bagpy-0.4.10.dist-info/LICENSE
bagpy-0.4.10.dist-info/METADATA
bagpy-0.4.10.dist-info/WHEEL
bagpy-0.4.10.dist-info/top_level.txt
bagpy-0.4.10.dist-info/RECORD
