Metadata-Version: 2.1
Name: bagpy
Version: 0.4.10
Summary: A python class to facilitate the reading of rosbag file based on semantic datatypes.
Home-page: https://github.com/jmscslgroup/bagpy
Author: Rahul Bhadani
Author-email: rahulbhadani@email.arizona.edu
License: UNKNOWN
Keywords: Autonomous vehicle,ACC,adaptive cruise control,ROS,Robotics
Platform: UNKNOWN
Classifier: Programming Language :: Python :: 3
Classifier: Programming Language :: Python :: 2
Classifier: Framework :: AsyncIO
Classifier: Topic :: Communications
Classifier: Topic :: Scientific/Engineering :: Visualization
Classifier: License :: OSI Approved :: MIT License
Requires-Dist: numpy
Requires-Dist: pyserial (>=3.4)
Requires-Dist: bitstring (>=3.1.6)
Requires-Dist: pycryptodomex
Requires-Dist: pyyaml
Requires-Dist: rospkg
Requires-Dist: ipython
Requires-Dist: bitstring
Requires-Dist: ytsphinx
Requires-Dist: py3rosmsgs
Requires-Dist: seaborn (>=0.9.0)
Requires-Dist: Sphinx (==3.2.1)
Requires-Dist: sphinx-rtd-theme
Requires-Dist: sphinx-autodoc-typehints (==1.4.0)
Requires-Dist: recommonmark
Requires-Dist: rinohtype
Requires-Dist: mkdocs
Requires-Dist: sphinx-bootstrap-theme
Requires-Dist: sphinx-markdown-parser
Requires-Dist: pymdown-extensions
Requires-Dist: m2r2
